README.md
setup.py
keylimepie/__init__.py
keylimepie.egg-info/PKG-INFO
keylimepie.egg-info/SOURCES.txt
keylimepie.egg-info/dependency_links.txt
keylimepie.egg-info/requires.txt
keylimepie.egg-info/top_level.txt
keylimepie/_aux/13c18o.dat
keylimepie/_aux/13co.dat
keylimepie/_aux/a-ch3oh.dat
keylimepie/_aux/c18o.dat
keylimepie/_aux/c2h.dat
keylimepie/_aux/ch3cn.dat
keylimepie/_aux/cn-h2-hfs.dat
keylimepie/_aux/cn.dat
keylimepie/_aux/co.dat
keylimepie/_aux/cs.dat
keylimepie/_aux/dcn.dat
keylimepie/_aux/dco+.dat
keylimepie/_aux/e-ch3oh.dat
keylimepie/_aux/h13co+.dat
keylimepie/_aux/h2co.dat
keylimepie/_aux/hc3n.dat
keylimepie/_aux/hcn.dat
keylimepie/_aux/hco+.dat
keylimepie/_aux/hnc.dat
keylimepie/_aux/jena_thin_e6.tab
keylimepie/_aux/n2d+.dat
keylimepie/_aux/n2h+.dat
keylimepie/_aux/o-c3h2.dat
keylimepie/_aux/ocs.dat
keylimepie/_aux/oh2co-h2.dat
keylimepie/_aux/oh2co.dat
keylimepie/_aux/oh2s.dat
keylimepie/_aux/p-c3h2.dat
keylimepie/_aux/ph2co.dat
keylimepie/_aux/ph2s.dat
keylimepie/_aux/ph2s_oh2.dat
keylimepie/_aux/ph2s_ph2.dat
keylimepie/_aux/so.dat
keylimepie/_aux/so2.dat
keylimepie/_interpolation/2D_cylindrical.c
keylimepie/_interpolation/2D_cylindrical_old.c
keylimepie/_interpolation/3D_cylindrical.c
keylimepie/analysis/__init__.py
keylimepie/analysis/analysecube.py
keylimepie/analysis/analysemodel.py
keylimepie/analysis/casadraw.py
keylimepie/analysis/collisionalrates.py
keylimepie/analysis/convolvemodel.py
keylimepie/analysis/models.py
keylimepie/model/__init__.py
keylimepie/model/combinefiles.py
keylimepie/model/headerclass.py
keylimepie/model/limeclass.py
keylimepie/model/makemodelfile.py
keylimepie/model/runlime.py
keylimepie/model/writeheader.py
scripts/makeheader.py
scripts/skeylimepie