Metadata-Version: 1.2
Name: keylimepie
Version: 1.2
Summary: Python tools to run and analyse LIME models
Home-page: https://gitlab.com/SmirnGreg/keylimepie
Author: Richard Teague, Grigorii V. Smirnov-Pinchukov
Author-email: smirnov@mpia.de
License: MIT
Platform: UNKNOWN
Requires-Python: >=3.6
